scAGDE/__init__.py
scAGDE/layer.py
scAGDE/loss.py
scAGDE/mclust.py
scAGDE/model.py
scAGDE/trainer.py
scAGDE/utils.py
scAGDE-0.0.18.dist-info/LICENSE
scAGDE-0.0.18.dist-info/METADATA
scAGDE-0.0.18.dist-info/WHEEL
scAGDE-0.0.18.dist-info/top_level.txt
scAGDE-0.0.18.dist-info/RECORD
