Metadata-Version: 2.1
Name: scAGDE
Version: 0.0.18
Summary: scAGDE Python package
Home-page: https://github.com/Hgy1014/scAGDE
Author: Gaoyang Hao
Author-email: <haogy22@mails.jlu.edu.cn>
Keywords: python,first package
Classifier: Development Status :: 3 - Alpha
Classifier: Intended Audience :: Education
Classifier: Programming Language :: Python :: 2
Classifier: Programming Language :: Python :: 3
Classifier: Operating System :: MacOS :: MacOS X
Classifier: Operating System :: Microsoft :: Windows
License-File: LICENSE
